{
  "version": "0.2.0",
  "description": "MetaMask Snap for Nostr",
  "proposedName": "Nostr Snap",
  "repository": {
    "type": "git",
    "url": "https://github.com/MetaMask/template-snap-monorepo.git"
  },
  "source": {
    "shasum": "9FSqsNotKTK65r0TQCpunm5VSZ1kV7oNbgDeSflHFs8=",
    "location": {
      "npm": {
        "filePath": "dist/bundle.js",
        "iconPath": "images/icon.svg",
        "packageName": "snap",
        "registry": "https://registry.npmjs.org/"
      }
    }
  },
  "initialPermissions": {
    "snap_dialog": {},
    "endowment:rpc": {
      "dapps": true,
      "snaps": false
    },
    "endowment:network-access": {}
  },
  "manifestVersion": "0.1"
}
